mq_http_aliyun_sdk/__init__.py
mq_http_aliyun_sdk/mq_client.py
mq_http_aliyun_sdk/mq_consumer.py
mq_http_aliyun_sdk/mq_exception.py
mq_http_aliyun_sdk/mq_http.py
mq_http_aliyun_sdk/mq_producer.py
mq_http_aliyun_sdk/mq_request.py
mq_http_aliyun_sdk/mq_tool.py
mq_http_aliyun_sdk/mq_xml_handler.py
mq_http_aliyun_sdk/pkg_info.py
mq_http_aliyun_sdk-1.0.0.dist-info/LICENSE
mq_http_aliyun_sdk-1.0.0.dist-info/METADATA
mq_http_aliyun_sdk-1.0.0.dist-info/WHEEL
mq_http_aliyun_sdk-1.0.0.dist-info/top_level.txt
mq_http_aliyun_sdk-1.0.0.dist-info/RECORD
