Metadata-Version: 2.1
Name: mq-http-aliyun-sdk
Version: 1.0.0
Summary: Aliyun Message Queue(MQ) Http Python SDK
Home-page: https://github.com/aliyunmq/mq-http-python-sdk
Author: ahrli
Author-email: ahrli_c@163.com
License: MIT
Platform: UNKNOWN
